mavros_python_examples/__init__.py
mavros_python_examples/rospyHandler.py
mavros_python_examples/roverHandler.py
mavros_python_examples/topicService.py
mavros_python_examples-0.0.3.dist-info/LICENSE
mavros_python_examples-0.0.3.dist-info/METADATA
mavros_python_examples-0.0.3.dist-info/WHEEL
mavros_python_examples-0.0.3.dist-info/top_level.txt
mavros_python_examples-0.0.3.dist-info/RECORD
