Metadata-Version: 2.1
Name: mavros-python-examples
Version: 0.0.3
Summary: MAVROS examples
Home-page: https://github.com/masoudir/mavros_python_examples
Author: Masoud Iranmehr
Author-email: masoud.iranmehr@gmail.com
License: UNKNOWN
Platform: UNKNOWN
Classifier: Programming Language :: Python :: 3
Classifier: License :: OSI Approved :: MIT License
Classifier: Operating System :: OS Independent
Requires-Python: >=3.6
